Metadata-Version: 2.1
Name: symbolic-dynamics
Version: 0.1.1
Summary: A symbolic dynamics package for Python
Home-page: https://github.com/jzc/symbolic-dynamics
Author: Justin Cai
Author-email: jc@justincai.com
License: MIT
Platform: UNKNOWN
Requires-Python: >=3.8
License-File: LICENSE
